maskedtensor/__init__.py
maskedtensor/binary.py
maskedtensor/core.py
maskedtensor/creation.py
maskedtensor/functions.py
maskedtensor/matmul.py
maskedtensor/passthrough.py
maskedtensor/reductions.py
maskedtensor/unary.py
maskedtensor/version.py
maskedtensor-0.10.0.dist-info/LICENSE
maskedtensor-0.10.0.dist-info/METADATA
maskedtensor-0.10.0.dist-info/WHEEL
maskedtensor-0.10.0.dist-info/top_level.txt
maskedtensor-0.10.0.dist-info/zip-safe
maskedtensor-0.10.0.dist-info/RECORD
