Metadata-Version: 2.1
Name: maskedtensor
Version: 0.10.0
Summary: MaskedTensors for PyTorch
Home-page: https://github.com/pytorch/maskedtensor
Author: PyTorch Core Team
License: UNKNOWN
Platform: UNKNOWN
Classifier: Programming Language :: Python :: 3
Classifier: Operating System :: OS Independent
License-File: LICENSE
Requires-Dist: torch (<=1.12,>=1.11)
